wowool/apps/numbers/__init__.py
wowool/apps/numbers/config.py
wowool/numbers/app_id.py
wowool/numbers/currency.py
wowool/numbers/numbers.py
wowool/numbers/units.py
wowool_numbers-2.1.4.dist-info/METADATA
wowool_numbers-2.1.4.dist-info/WHEEL
wowool_numbers-2.1.4.dist-info/top_level.txt
wowool_numbers-2.1.4.dist-info/RECORD
