Metadata-Version: 2.4
Name: wowool-numbers
Version: 2.1.4
Summary: Wowool Numbers
Home-page: https://www.wowool.com/
Author: Wowool
Author-email: info@wowool.com
Requires-Python: >=3.10
Requires-Dist: wowool-sdk<3.6.0,>=3.5.3
Dynamic: author
Dynamic: author-email
Dynamic: description
Dynamic: description-content-type
Dynamic: home-page
Dynamic: requires-dist
Dynamic: requires-python
Dynamic: summary
